Voting Machine in Verilog/modeControl.v
`timescale 1ns / 1ps

module modeControl(
input clock,
input reset,
input mode,
input valid_vote_casted,
input [7:0] candidate1_vote,
input [7:0] candidate2_vote,
input [7:0] candidate3_vote,
input [7:0] candidate4_vote,
input candidate1_button_press,
input candidate2_button_press,
input candidate3_button_press,
input candidate4_button_press,
output reg [7:0] leds
    );
	
reg [30:0] counter;

always @(posedge clock)
begin
    if(reset)
        counter <= 0;   //Whenever reset is pressed, counter started from 0
    else if(valid_vote_casted) //If a valid vote is casted, counter becomes 1
        counter <= counter + 1;
    else if(counter !=0 & counter < 10)//If counter is not 0, increment it till 10
        counter <= counter + 1;
    else //Once counter becomes 10, reset it to zero
        counter <= 0;
end    
    
always @(posedge clock)
begin
    if(reset)
        leds <= 0;
    else
    begin
        if(mode == 0 &  counter > 0 ) //mode0 -> voting mode, mode 1 -> result mode
            leds <= 8'hFF;
        else if(mode == 0)
            leds <= 8'h00;
        else if(mode == 1) //result mode
        begin
            if(candidate1_button_press)
                leds <= candidate1_vote;
            else if(candidate2_button_press)
                leds <= candidate2_vote;
            else if(candidate3_button_press)
                leds <= candidate3_vote;
            else if(candidate4_button_press)
                leds <= candidate4_vote;
        end
    end  
end
    
endmodule

Voting Machine in Verilog/voteLogger.v
`timescale 1ns / 1ps

module voteLogger(
input clock,
input reset,
input mode,
input cand1_vote_valid,
input cand2_vote_valid,
input cand3_vote_valid,
input cand4_vote_valid,
output reg [7:0] cand1_vote_recvd,
output reg [7:0] cand2_vote_recvd,
output reg [7:0] cand3_vote_recvd,
output reg [7:0] cand4_vote_recvd
);


always @(posedge clock)
begin
    if(reset)
    begin
        cand1_vote_recvd <= 0;
        cand2_vote_recvd <= 0;
        cand3_vote_recvd <= 0;
        cand4_vote_recvd <= 0;
    end
    else
    begin
        if(cand1_vote_valid & mode==0)
            cand1_vote_recvd <= cand1_vote_recvd + 1;
        else if(cand2_vote_valid & mode==0)
            cand2_vote_recvd <= cand2_vote_recvd + 1;
        else if(cand3_vote_valid & mode==0)
            cand3_vote_recvd <= cand3_vote_recvd + 1;
        else if(cand4_vote_valid & mode==0)
            cand4_vote_recvd <= cand4_vote_recvd + 1;
    end
end

endmodule

Voting Machine in Verilog/work/buttonControl.v
`timescale 1ns / 1ps

module buttonControl(
input clock,
input reset,
input button,
output reg valid_vote
);

reg [30:0] counter;

always @(posedge clock)
begin
    if(reset)
        counter <= 0;
    else
    begin
        if(button & counter < 11)
            counter <= counter + 1;
        else if(!button)
            counter <= 0;
    end
end

always @(posedge clock)
begin
    if(reset)
        valid_vote <= 1'b0;
    else
    begin
        if(counter == 10)
            valid_vote <= 1'b1;
        else
            valid_vote <= 1'b0;
    end
end

endmodule

Voting Machine in Verilog/votingMachine.v
`timescale 1ns / 1ps

module votingMachine(
input clock,
input reset,
input mode,
input button1,
input button2,
input button3,
input button4,
output [7:0] led
);

wire valid_vote_1;
wire valid_vote_2;
wire valid_vote_3;
wire valid_vote_4;
wire [7:0] cand1_vote_recvd;
wire [7:0] cand2_vote_recvd;
wire [7:0] cand3_vote_recvd;
wire [7:0] cand4_vote_recvd;
wire anyValidVote;

assign anyValidVote = valid_vote_1|valid_vote_2|valid_vote_3|valid_vote_4;

buttonControl bc1(
.clock(clock),
.reset(reset),
.button(button1),
.valid_vote(valid_vote_1)
);

buttonControl bc2(
.clock(clock),
.reset(reset),
.button(button2),
.valid_vote(valid_vote_2)
);

buttonControl bc3(
.clock(clock),
.reset(reset),
.button(button3),//
.valid_vote(valid_vote_3)
);

buttonControl bc4(
.clock(clock),
.reset(reset),
.button(button4),
.valid_vote(valid_vote_4)
);



voteLogger VL(
.clock(clock),
.reset(reset),
.mode(mode),
.cand1_vote_valid(valid_vote_1),
.cand2_vote_valid(valid_vote_2),
.cand3_vote_valid(valid_vote_3),
.cand4_vote_valid(valid_vote_4),
.cand1_vote_recvd(cand1_vote_recvd),
.cand2_vote_recvd(cand2_vote_recvd),
.cand3_vote_recvd(cand3_vote_recvd),
.cand4_vote_recvd(cand4_vote_recvd)
);


modeControl MC(
.clock(clock),
.reset(reset),
.mode(mode),
.valid_vote_casted(anyValidVote),
.candidate1_vote(cand1_vote_recvd),
.candidate2_vote(cand2_vote_recvd),
.candidate3_vote(cand3_vote_recvd),
.candidate4_vote(cand4_vote_recvd),
.candidate1_button_press(valid_vote_1),
.candidate2_button_press(valid_vote_2),
.candidate3_button_press(valid_vote_3),
.candidate4_button_press(valid_vote_4),
.leds(led)
    );

endmodule

Voting Machine in Verilog/work/votingMachine_tb.v
`timescale 1ns / 1ps

module votingMachine_tb;

	// Inputs
	reg clock;
	reg reset;
	reg mode;
	reg button1;
	reg button2;
	reg button3;
	reg button4;

	// Outputs
	wire [7:0] led;

	// Instantiate the Unit Under Test (UUT)
	votingMachine uut (
		.clock(clock), 
		.reset(reset), 
		.mode(mode), 
		.button1(button1), 
		.button2(button2), 
		.button3(button3), 
		.button4(button4), 
		.led(led)
	);
  
  	initial begin
      clock = 0;
      forever #5 clock = ~clock;
     end	
        
  	initial begin
		// Initialize Inputs
		reset = 1; mode = 0; button1 = 0;button2 = 0; button3 = 0; button4 = 0;
		// Wait 100 ns for global reset to finish
		#100;
        
		// Add stimulus here
		
      #100 reset = 0; mode = 0; button1 = 0;button2 = 0; button3 = 0; button4 =0;
      #5reset = 0; mode = 0; button1 = 1;button2 = 0; button3 = 0; button4 = 0;
      #10reset = 0; mode = 0; button1 = 0;button2 = 0; button3 = 0; button4 =0;
      #5reset = 0; mode = 0; button1 = 1;button2 = 0; button3 = 0; button4 = 0;
      #200 reset = 0; mode = 0; button1 = 0;button2 = 0; button3 = 0; button4 =0;
      #5reset = 0; mode = 0; button1 = 0;button2 = 0; button3 = 0; button4 =0;
      #10reset = 0; mode = 0; button1 = 0;button2 = 0; button3 = 0; button4 =0;
      #5reset = 0; mode = 0; button1 = 0;button2 = 0; button3 = 0; button4 =0;
      
      #5reset = 0; mode = 0; button1 = 0;button2 = 1; button3 = 0; button4 = 0;
      #200 reset = 0; mode = 0; button1 = 0;button2 = 0; button3 = 0; button4 =0;
      #5reset = 0; mode = 0; button1 = 0;button2 = 0; button3 = 0; button4 =0;
      #10reset = 0; mode = 0; button1 = 0;button2 = 0; button3 = 0; button4 =0;
      #5reset = 0; mode = 0; button1 = 0;button2 = 0; button3 = 0; button4 =0;
      
      #5reset = 0; mode = 0; button1 = 0;button2 = 1; button3 = 0; button4 = 0;
      #200 reset = 0; mode = 0; button1 = 0;button2 = 0; button3 = 0; button4 =0;
      #5reset = 0; mode = 0; button1 = 0;button2 = 0; button3 = 0; button4 =0;
      #10reset = 0; mode = 0; button1 = 0;button2 = 0; button3 = 0; button4 =0;
      #5reset = 0; mode = 0; button1 = 0;button2 = 0; button3 = 0; button4 =0;
      
      #5reset = 0; mode = 1; button1 = 0;button2 = 1; button3 = 0; button4 = 0;
      #200 reset = 0; mode = 1; button1 = 0;button2 = 0; button3 = 1; button4 =0;
      #5reset = 0; mode = 0; button1 = 0;button2 = 0; button3 = 0; button4 =0;
      #10reset = 0; mode = 0; button1 = 0;button2 = 0; button3 = 0; button4 =0;
      #5reset = 0; mode = 0; button1 = 0;button2 = 0; button3 = 0; button4 =0;
      
      #5reset = 0; mode = 0; button1 = 0;button2 = 0; button3 = 1; button4 = 0;
      #200 reset = 0; mode = 0; button1 = 0;button2 = 0; button3 = 0; button4 =0;
      #5reset = 0; mode = 0; button1 = 0;button2 = 0; button3 = 0; button4 =0;
      #10reset = 0; mode = 0; button1 = 0;button2 = 0; button3 = 0; button4 =0;
      #5reset = 0; mode = 0; button1 = 0;button2 = 0; button3 = 0; button4 =0;
      
      #5reset = 0; mode = 1; button1 = 0;button2 = 0; button3 = 1; button4 = 0;
      #200 reset = 0; mode = 1; button1 = 0;button2 = 0; button3 = 1; button4 =0;
      #5reset = 0; mode = 0; button1 = 0;button2 = 0; button3 = 0; button4 =0;
      #10reset = 0; mode = 0; button1 = 0;button2 = 0; button3 = 0; button4 =0;
      #5reset = 0; mode = 0; button1 = 0;button2 = 0; button3 = 0; button4 =0;
      
      $finish;
      
	end
  
  initial 
  	begin 
    $dumpvars;  
      $dumpfile("dump.vcd");
   
  	end

  initial
    $monitor($time, "mode = %b, button1 = %b, button2 = %b,button3 = %b, button4 = %b, led = %d",mode,button1,button2,button3,button4,led);

endmodule

Voting Machine in Verilog/dump.vcd
$date
	Thu Apr 27 18:56:56 2023
$end
$version
	ModelSim Version 10.5b
$end
$timescale
	1ps
$end

$scope module votingMachine_tb $end
$var reg 1 ! clock $end
$var reg 1 " reset $end
$var reg 1 # mode $end
$var reg 1 $ button1 $end
$var reg 1 % button2 $end
$var reg 1 & button3 $end
$var reg 1 ' button4 $end
$var wire 1 ( led [7] $end
$var wire 1 ) led [6] $end
$var wire 1 * led [5] $end
$var wire 1 + led [4] $end
$var wire 1 , led [3] $end
$var wire 1 - led [2] $end
$var wire 1 . led [1] $end
$var wire 1 / led [0] $end

$scope module uut $end
$var wire 1 0 clock $end
$var wire 1 1 reset $end
$var wire 1 2 mode $end
$var wire 1 3 button1 $end
$var wire 1 4 button2 $end
$var wire 1 5 button3 $end
$var wire 1 6 button4 $end
$var wire 1 ( led [7] $end
$var wire 1 ) led [6] $end
$var wire 1 * led [5] $end
$var wire 1 + led [4] $end
$var wire 1 , led [3] $end
$var wire 1 - led [2] $end
$var wire 1 . led [1] $end
$var wire 1 / led [0] $end
$var wire 1 7 valid_vote_1 $end
$var wire 1 8 valid_vote_2 $end
$var wire 1 9 valid_vote_3 $end
$var wire 1 : valid_vote_4 $end
$var wire 1 ; cand1_vote_recvd [7] $end
$var wire 1 < cand1_vote_recvd [6] $end
$var wire 1 = cand1_vote_recvd [5] $end
$var wire 1 > cand1_vote_recvd [4] $end
$var wire 1 ? cand1_vote_recvd [3] $end
$var wire 1 @ cand1_vote_recvd [2] $end
$var wire 1 A cand1_vote_recvd [1] $end
$var wire 1 B cand1_vote_recvd [0] $end
$var wire 1 C cand2_vote_recvd [7] $end
$var wire 1 D cand2_vote_recvd [6] $end
$var wire 1 E cand2_vote_recvd [5] $end
$var wire 1 F cand2_vote_recvd [4] $end
$var wire 1 G cand2_vote_recvd [3] $end
$var wire 1 H cand2_vote_recvd [2] $end
$var wire 1 I cand2_vote_recvd [1] $end
$var wire 1 J cand2_vote_recvd [0] $end
$var wire 1 K cand3_vote_recvd [7] $end
$var wire 1 L cand3_vote_recvd [6] $end
$var wire 1 M cand3_vote_recvd [5] $end
$var wire 1 N cand3_vote_recvd [4] $end
$var wire 1 O cand3_vote_recvd [3] $end
$var wire 1 P cand3_vote_recvd [2] $end
$var wire 1 Q cand3_vote_recvd [1] $end
$var wire 1 R cand3_vote_recvd [0] $end
$var wire 1 S cand4_vote_recvd [7] $end
$var wire 1 T cand4_vote_recvd [6] $end
$var wire 1 U cand4_vote_recvd [5] $end
$var wire 1 V cand4_vote_recvd [4] $end
$var wire 1 W cand4_vote_recvd [3] $end
$var wire 1 X cand4_vote_recvd [2] $end
$var wire 1 Y cand4_vote_recvd [1] $end
$var wire 1 Z cand4_vote_recvd [0] $end
$var wire 1 [ anyValidVote $end

$scope module bc1 $end
$var wire 1 0 clock $end
$var wire 1 1 reset $end
$var wire 1 3 button $end
$var reg 1 \ valid_vote $end
$var reg 31 ] counter [30:0] $end
$upscope $end

$scope module bc2 $end
$var wire 1 0 clock $end
$var wire 1 1 reset $end
$var wire 1 4 button $end
$var reg 1 ^ valid_vote $end
$var reg 31 _ counter [30:0] $end
$upscope $end

$scope module bc3 $end
$var wire 1 0 clock $end
$var wire 1 1 reset $end
$var wire 1 5 button $end
$var reg 1 ` valid_vote $end
$var reg 31 a counter [30:0] $end
$upscope $end

$scope module bc4 $end
$var wire 1 0 clock $end
$var wire 1 1 reset $end
$var wire 1 6 button $end
$var reg 1 b valid_vote $end
$var reg 31 c counter [30:0] $end
$upscope $end

$scope module VL $end
$var wire 1 0 clock $end
$var wire 1 1 reset $end
$var wire 1 2 mode $end
$var wire 1 7 cand1_vote_valid $end
$var wire 1 8 cand2_vote_valid $end
$var wire 1 9 cand3_vote_valid $end
$var wire 1 : cand4_vote_valid $end
$var reg 8 d cand1_vote_recvd [7:0] $end
$var reg 8 e cand2_vote_recvd [7:0] $end
$var reg 8 f cand3_vote_recvd [7:0] $end
$var reg 8 g cand4_vote_recvd [7:0] $end
$upscope $end

$scope module MC $end
$var wire 1 0 clock $end
$var wire 1 1 reset $end
$var wire 1 2 mode $end
$var wire 1 [ valid_vote_casted $end
$var wire 1 ; candidate1_vote [7] $end
$var wire 1 < candidate1_vote [6] $end
$var wire 1 = candidate1_vote [5] $end
$var wire 1 > candidate1_vote [4] $end
$var wire 1 ? candidate1_vote [3] $end
$var wire 1 @ candidate1_vote [2] $end
$var wire 1 A candidate1_vote [1] $end
$var wire 1 B candidate1_vote [0] $end
$var wire 1 C candidate2_vote [7] $end
$var wire 1 D candidate2_vote [6] $end
$var wire 1 E candidate2_vote [5] $end
$var wire 1 F candidate2_vote [4] $end
$var wire 1 G candidate2_vote [3] $end
$var wire 1 H candidate2_vote [2] $end
$var wire 1 I candidate2_vote [1] $end
$var wire 1 J candidate2_vote [0] $end
$var wire 1 K candidate3_vote [7] $end
$var wire 1 L candidate3_vote [6] $end
$var wire 1 M candidate3_vote [5] $end
$var wire 1 N candidate3_vote [4] $end
$var wire 1 O candidate3_vote [3] $end
$var wire 1 P candidate3_vote [2] $end
$var wire 1 Q candidate3_vote [1] $end
$var wire 1 R candidate3_vote [0] $end
$var wire 1 S candidate4_vote [7] $end
$var wire 1 T candidate4_vote [6] $end
$var wire 1 U candidate4_vote [5] $end
$var wire 1 V candidate4_vote [4] $end
$var wire 1 W candidate4_vote [3] $end
$var wire 1 X candidate4_vote [2] $end
$var wire 1 Y candidate4_vote [1] $end
$var wire 1 Z candidate4_vote [0] $end
$var wire 1 7 candidate1_button_press $end
$var wire 1 8 candidate2_button_press $end
$var wire 1 9 candidate3_button_press $end
$var wire 1 : candidate4_button_press $end
$var reg 8 h leds [7:0] $end
$var reg 31 i counter [30:0] $end
$upscope $end
$upscope $end
$upscope $end
$enddefinitions $end
#0
$dumpvars
0!
1"
0#
0$
0%
0&
0'
x\
bx ]
x^
bx _
x`
bx a
xb
bx c
bx d
bx e
bx f
bx g
bx h
bx i
x/
x.
x-
x,
x+
x*
x)
x(
x7
x8
x9
x:
xB
xA
x@
x?
x>
x=
x<
x;
xJ
xI
xH
xG
xF
xE
xD
xC
xR
xQ
xP
xO
xN
xM
xL
xK
xZ
xY
xX
xW
xV
xU
xT
xS
x[
06
05
04
03
02
11
00
$end
#5000
1!
10
b0 ]
0\
b0 _
0^
b0 a
0`
b0 c
0b
b0 d
b0 e
b0 f
b0 g
b0 i
b0 h
07
08
09
0:
0/
0.
0-
0,
0+
0*
0)
0(
0Z
0Y
0X
0W
0V
0U
0T
0S
0R
0Q
0P
0O
0N
0M
0L
0K
0J
0I
0H
0G
0F
0E
0D
0C
0B
0A
0@
0?
0>
0=
0<
0;
0[
#10000
0!
00
#15000
1!
10
#20000
0!
00
#25000
1!
10
#30000
0!
00
#35000
1!
10
#40000
0!
00
#45000
1!
10
#50000
0!
00
#55000
1!
10
#60000
0!
00
#65000
1!
10
#70000
0!
00
#75000
1!
10
#80000
0!
00
#85000
1!
10
#90000
0!
00
#95000
1!
10
#100000
0!
00
#105000
1!
10
#110000
0!
00
#115000
1!
10
#120000
0!
00
#125000
1!
10
#130000
0!
00
#135000
1!
10
#140000
0!
00
#145000
1!
10
#150000
0!
00
#155000
1!
10
#160000
0!
00
#165000
1!
10
#170000
0!
00
#175000
1!
10
#180000
0!
00
#185000
1!
10
#190000
0!
00
#195000
1!
10
#200000
0"
0!
01
00
#205000
1$
1!
13
10
b1 ]
#210000
0!
00
#215000
0$
1!
03
10
b0 ]
#220000
1$
0!
13
00
#225000
1!
10
b1 ]
#230000
0!
00
#235000
1!
10
b10 ]
#240000
0!
00
#245000
1!
10
b11 ]
#250000
0!
00
#255000
1!
10
b100 ]
#260000
0!
00
#265000
1!
10
b101 ]
#270000
0!
00
#275000
1!
10
b110 ]
#280000
0!
00
#285000
1!
10
b111 ]
#290000
0!
00
#295000
1!
10
b1000 ]
#300000
0!
00
#305000
1!
10
b1001 ]
#310000
0!
00
#315000
1!
10
b1010 ]
#320000
0!
00
#325000
1!
10
b1011 ]
1\
17
1[
#330000
0!
00
#335000
1!
10
0\
b1 d
b1 i
07
1B
0[
#340000
0!
00
#345000
1!
10
b10 i
b11111111 h
1/
1.
1-
1,
1+
1*
1)
1(
#350000
0!
00
#355000
1!
10
b11 i
#360000
0!
00
#365000
1!
10
b100 i
#370000
0!
00
#375000
1!
10
b101 i
#380000
0!
00
#385000
1!
10
b110 i
#390000
0!
00
#395000
1!
10
b111 i
#400000
0!
00
#405000
1!
10
b1000 i
#410000
0!
00
#415000
1!
10
b1001 i
#420000
0$
0!
03
00
#425000
1!
10
b0 ]
b1010 i
#430000
0!
00
#435000
1!
10
b0 i
#440000
0!
00
#445000
1%
1!
14
10
b1 _
b0 h
0/
0.
0-
0,
0+
0*
0)
0(
#450000
0!
00
#455000
1!
10
b10 _
#460000
0!
00
#465000
1!
10
b11 _
#470000
0!
00
#475000
1!
10
b100 _
#480000
0!
00
#485000
1!
10
b101 _
#490000
0!
00
#495000
1!
10
b110 _
#500000
0!
00
#505000
1!
10
b111 _
#510000
0!
00
#515000
1!
10
b1000 _
#520000
0!
00
#525000
1!
10
b1001 _
#530000
0!
00
#535000
1!
10
b1010 _
#540000
0!
00
#545000
1!
10
b1011 _
1^
18
1[
#550000
0!
00
#555000
1!
10
0^
b1 e
b1 i
08
1J
0[
#560000
0!
00
#565000
1!
10
b10 i
b11111111 h
1/
1.
1-
1,
1+
1*
1)
1(
#570000
0!
00
#575000
1!
10
b11 i
#580000
0!
00
#585000
1!
10
b100 i
#590000
0!
00
#595000
1!
10
b101 i
#600000
0!
00
#605000
1!
10
b110 i
#610000
0!
00
#615000
1!
10
b111 i
#620000
0!
00
#625000
1!
10
b1000 i
#630000
0!
00
#635000
1!
10
b1001 i
#640000
0!
00
#645000
0%
1!
04
10
b0 _
b1010 i
#650000
0!
00
#655000
1!
10
b0 i
#660000
0!
00
#665000
1!
10
b0 h
0/
0.
0-
0,
0+
0*
0)
0(
#670000
1%
0!
14
00
#675000
1!
10
b1 _
#680000
0!
00
#685000
1!
10
b10 _
#690000
0!
00
#695000
1!
10
b11 _
#700000
0!
00
#705000
1!
10
b100 _
#710000
0!
00
#715000
1!
10
b101 _
#720000
0!
00
#725000
1!
10
b110 _
#730000
0!
00
#735000
1!
10
b111 _
#740000
0!
00
#745000
1!
10
b1000 _
#750000
0!
00
#755000
1!
10
b1001 _
#760000
0!
00
#765000
1!
10
b1010 _
#770000
0!
00
#775000
1!
10
b1011 _
1^
18
1[
#780000
0!
00
#785000
1!
10
0^
b10 e
b1 i
08
0J
1I
0[
#790000
0!
00
#795000
1!
10
b10 i
b11111111 h
1/
1.
1-
1,
1+
1*
1)
1(
#800000
0!
00
#805000
1!
10
b11 i
#810000
0!
00
#815000
1!
10
b100 i
#820000
0!
00
#825000
1!
10
b101 i
#830000
0!
00
#835000
1!
10
b110 i
#840000
0!
00
#845000
1!
10
b111 i
#850000
0!
00
#855000
1!
10
b1000 i
#860000
0!
00
#865000
1!
10
b1001 i
#870000
0%
0!
04
00
#875000
1!
10
b0 _
b1010 i
#880000
0!
00
#885000
1!
10
b0 i
#890000
0!
00
#895000
1#
1%
1!
12
14
10
b1 _
#900000
0!
00
#905000
1!
10
b10 _
#910000
0!
00
#915000
1!
10
b11 _
#920000
0!
00
#925000
1!
10
b100 _
#930000
0!
00
#935000
1!
10
b101 _
#940000
0!
00
#945000
1!
10
b110 _
#950000
0!
00
#955000
1!
10
b111 _
#960000
0!
00
#965000
1!
10
b1000 _
#970000
0!
00
#975000
1!
10
b1001 _
#980000
0!
00
#985000
1!
10
b1010 _
#990000
0!
00
#995000
1!
10
b1011 _
1^
18
1[
#1000000
0!
00
#1005000
1!
10
0^
b1 i
b10 h
08
0/
0-
0,
0+
0*
0)
0(
0[
#1010000
0!
00
#1015000
1!
10
b10 i
#1020000
0!
00
#1025000
1!
10
b11 i
#1030000
0!
00
#1035000
1!
10
b100 i
#1040000
0!
00
#1045000
1!
10
b101 i
#1050000
0!
00
#1055000
1!
10
b110 i
#1060000
0!
00
#1065000
1!
10
b111 i
#1070000
0!
00
#1075000
1!
10
b1000 i
#1080000
0!
00
#1085000
1!
10
b1001 i
#1090000
0!
00
#1095000
0%
1&
1!
04
15
10
b0 _
b1 a
b1010 i
#1100000
0#
0&
0!
02
05
00
#1105000
1!
10
b0 a
b0 i
b11111111 h
1/
1-
1,
1+
1*
1)
1(
#1110000
0!
00
#1115000
1!
10
b0 h
0/
0.
0-
0,
0+
0*
0)
0(
#1120000
1&
0!
15
00
#1125000
1!
10
b1 a
#1130000
0!
00
#1135000
1!
10
b10 a
#1140000
0!
00
#1145000
1!
10
b11 a
#1150000
0!
00
#1155000
1!
10
b100 a
#1160000
0!
00
#1165000
1!
10
b101 a
#1170000
0!
00
#1175000
1!
10
b110 a
#1180000
0!
00
#1185000
1!
10
b111 a
#1190000
0!
00
#1195000
1!
10
b1000 a
#1200000
0!
00
#1205000
1!
10
b1001 a
#1210000
0!
00
#1215000
1!
10
b1010 a
#1220000
0!
00
#1225000
1!
10
b1011 a
1`
19
1[
#1230000
0!
00
#1235000
1!
10
0`
b1 f
b1 i
09
1R
0[
#1240000
0!
00
#1245000
1!
10
b10 i
b11111111 h
1/
1.
1-
1,
1+
1*
1)
1(
#1250000
0!
00
#1255000
1!
10
b11 i
#1260000
0!
00
#1265000
1!
10
b100 i
#1270000
0!
00
#1275000
1!
10
b101 i
#1280000
0!
00
#1285000
1!
10
b110 i
#1290000
0!
00
#1295000
1!
10
b111 i
#1300000
0!
00
#1305000
1!
10
b1000 i
#1310000
0!
00
#1315000
1!
10
b1001 i
#1320000
0&
0!
05
00
#1325000
1!
10
b0 a
b1010 i
#1330000
0!
00
#1335000
1!
10
b0 i
#1340000
0!
00
#1345000
1#
1&
1!
12
15
10
b1 a
#1350000
0!
00
#1355000
1!
10
b10 a
#1360000
0!
00
#1365000
1!
10
b11 a
#1370000
0!
00
#1375000
1!
10
b100 a
#1380000
0!
00
#1385000
1!
10
b101 a
#1390000
0!
00
#1395000
1!
10
b110 a
#1400000
0!
00
#1405000
1!
10
b111 a
#1410000
0!
00
#1415000
1!
10
b1000 a
#1420000
0!
00
#1425000
1!
10
b1001 a
#1430000
0!
00
#1435000
1!
10
b1010 a
#1440000
0!
00
#1445000
1!
10
b1011 a
1`
19
1[
#1450000
0!
00
#1455000
1!
10
0`
b1 i
b1 h
09
0.
0-
0,
0+
0*
0)
0(
0[
#1460000
0!
00
#1465000
1!
10
b10 i
#1470000
0!
00
#1475000
1!
10
b11 i
#1480000
0!
00
#1485000
1!
10
b100 i
#1490000
0!
00
#1495000
1!
10
b101 i
#1500000
0!
00
#1505000
1!
10
b110 i
#1510000
0!
00
#1515000
1!
10
b111 i
#1520000
0!
00
#1525000
1!
10
b1000 i
#1530000
0!
00
#1535000
1!
10
b1001 i
#1540000
0!
00
#1545000
1!
10
b1010 i
#1550000
0#
0&
0!
02
05
00
#1555000
1!
10
b0 a
b0 i
b11111111 h
1.
1-
1,
1+
1*
1)
1(
